VidFlow/__main__.py
VidFlow/aggregate/ffmpeg_component.py
VidFlow/aggregate/filehandler_component.py
VidFlow/aggregate/kill_feed.png
VidFlow/aggregate/opencv_component.py
VidFlow/aggregate/red_threshold_kill_feed.png
VidFlow/aggregate/sift_keypoints.jpg
VidFlow/aggregate/sift_keypoints1.jpg
VidFlow/aggregate/utils.py
VidFlow/cli.py
VidFlow/dev_tool/__init__.py
VidFlow/dev_tool/decorator.py
VidFlow/dev_tool/utils.py
VidFlow/modules/pipeline_builder.py
VidFlow/modules/video_stream.py
VidFlow/modules/video_transition.py
VidFlow/pipes/__init__.py
VidFlow/pipes/action_stage.py
VidFlow/pipes/analyze_clip_stage.py
VidFlow/pipes/analyze_data_stage.py
VidFlow/pipes/compile_stage.py
VidFlow/pipes/data_cache_stage.py
VidFlow/pipes/dl_stage.py
VidFlow/pipes/entry_stage.py
VidFlow/pipes/test_stage.py
VidFlow/pipes/U_caster_mode.py
VidFlow/pipes/upload_stage.py
vidflow-0.1.2.dist-info/entry_points.txt
vidflow-0.1.2.dist-info/LICENSE
vidflow-0.1.2.dist-info/METADATA
vidflow-0.1.2.dist-info/WHEEL
vidflow-0.1.2.dist-info/RECORD
