Metadata-Version: 2.1
Name: VidFlow
Version: 0.1.2
Summary: making videos at lightspeed
License: MIT
Author: Andy Sit
Author-email: andysit173@gmail.com
Requires-Python: >=3.9,<4.0
Classifier: License :: OSI Approved :: MIT License
Classifier: Programming Language :: Python :: 3
Classifier: Programming Language :: Python :: 3.9
Classifier: Programming Language :: Python :: 3.10
Classifier: Programming Language :: Python :: 3.11
Classifier: Programming Language :: Python :: 3.12
Requires-Dist: asttokens (==2.4.1)
Requires-Dist: cachetools (==5.5.0)
Requires-Dist: certifi (==2024.6.2)
Requires-Dist: cffi (==1.16.0)
Requires-Dist: charset-normalizer (==3.3.2)
Requires-Dist: click (==8.1.7)
Requires-Dist: colorama (==0.4.6)
Requires-Dist: contourpy (==1.2.1)
Requires-Dist: cycler (==0.12.1)
Requires-Dist: executing (==2.0.1)
Requires-Dist: ffmpeg-python (==0.2.0)
Requires-Dist: filelock (==3.15.4)
Requires-Dist: fonttools (==4.53.0)
Requires-Dist: fsspec (==2024.6.1)
Requires-Dist: future (==1.0.0)
Requires-Dist: google-api-core (==2.19.1)
Requires-Dist: google-api-python-client (==2.142.0)
Requires-Dist: google-auth (==2.34.0)
Requires-Dist: google-auth-httplib2 (==0.2.0)
Requires-Dist: google-auth-oauthlib (==1.2.1)
Requires-Dist: googleapis-common-protos (==1.64.0)
Requires-Dist: httplib2 (==0.22.0)
Requires-Dist: icecream (==2.1.3)
Requires-Dist: idna (==3.7)
Requires-Dist: imageio (==2.34.1)
Requires-Dist: importlib-resources (==6.4.0)
Requires-Dist: jinja2 (==3.1.4)
Requires-Dist: joblib (==1.4.2)
Requires-Dist: kiwisolver (==1.4.5)
Requires-Dist: lazy-loader (==0.4)
Requires-Dist: llvmlite (==0.43.0)
Requires-Dist: markdown-it-py (==3.0.0)
Requires-Dist: markupsafe (==2.1.5)
Requires-Dist: matplotlib (==3.9.0)
Requires-Dist: mdurl (==0.1.2)
Requires-Dist: more-itertools (==10.4.0)
Requires-Dist: mpmath (==1.3.0)
Requires-Dist: networkx (==3.2.1)
Requires-Dist: numba (==0.60.0)
Requires-Dist: numpy (==1.26.4)
Requires-Dist: oauthlib (==3.2.2)
Requires-Dist: opencv-python (==4.10.0.82)
Requires-Dist: packaging (==24.0)
Requires-Dist: pandas (==2.2.2)
Requires-Dist: pillow (==10.3.0)
Requires-Dist: prompt-toolkit (==3.0.36)
Requires-Dist: proto-plus (==1.24.0)
Requires-Dist: protobuf (==5.27.3)
Requires-Dist: pyasn1 (==0.6.0)
Requires-Dist: pyasn1-modules (==0.4.0)
Requires-Dist: pycparser (==2.22)
Requires-Dist: pygments (==2.18.0)
Requires-Dist: pyparsing (==3.1.2)
Requires-Dist: python-dateutil (==2.9.0.post0)
Requires-Dist: pytz (==2024.1)
Requires-Dist: questionary (==2.0.1)
Requires-Dist: regex (==2024.7.24)
Requires-Dist: requests (==2.32.3)
Requires-Dist: requests-oauthlib (==2.0.0)
Requires-Dist: rich (==13.7.1)
Requires-Dist: rsa (==4.9)
Requires-Dist: scikit-image (==0.22.0)
Requires-Dist: scikit-learn (==1.5.0)
Requires-Dist: scipy (==1.13.1)
Requires-Dist: six (==1.16.0)
Requires-Dist: srt (==3.5.3)
Requires-Dist: sympy (==1.13.1)
Requires-Dist: threadpoolctl (==3.5.0)
Requires-Dist: tifffile (==2024.5.22)
Requires-Dist: tiktoken (==0.7.0)
Requires-Dist: tqdm (==4.66.4)
Requires-Dist: typing-extensions (==4.12.2)
Requires-Dist: tzdata (==2024.1)
Requires-Dist: uritemplate (==4.1.1)
Requires-Dist: urllib3 (==2.2.1)
Requires-Dist: vosk (==0.3.45)
Requires-Dist: wcwidth (==0.2.13)
Requires-Dist: websockets (==12.0)
Requires-Dist: zipp (==3.19.2)
